django_admin_keycloak/__init__.py
django_admin_keycloak/admin.py
django_admin_keycloak/apps.py
django_admin_keycloak/locale/ru/LC_MESSAGES/django.mo
django_admin_keycloak/locale/ru/LC_MESSAGES/django.po
django_admin_keycloak/management/__init__.py
django_admin_keycloak/management/commands/__init__.py
django_admin_keycloak/management/commands/update_static_providers.py
django_admin_keycloak/migrations/0001_initial.py
django_admin_keycloak/migrations/0002_rename_client_secret_key_keycloakprovider_client_secret_and_more.py
django_admin_keycloak/migrations/0003_keycloaksession.py
django_admin_keycloak/migrations/0004_delete_keycloaksession.py
django_admin_keycloak/migrations/0005_keycloaksession.py
django_admin_keycloak/migrations/0006_keycloakuser.py
django_admin_keycloak/migrations/0007_keycloakprovider_app_name.py
django_admin_keycloak/migrations/__init__.py
django_admin_keycloak/models.py
django_admin_keycloak/oidc.py
django_admin_keycloak/signals.py
django_admin_keycloak/static/admin/css/keycloak.css
django_admin_keycloak/static_settings.py
django_admin_keycloak/templates/admin/base.html
django_admin_keycloak/templates/admin/login.html
django_admin_keycloak/templates/django_admin_keycloak/auth_link.html
django_admin_keycloak/templates/django_admin_keycloak/login-error.html
django_admin_keycloak/templatetags/__init__.py
django_admin_keycloak/templatetags/keycloak.py
django_admin_keycloak/urls.py
django_admin_keycloak/utils.py
django_admin_keycloak/views.py
django_admin_keycloak-1.0.1.dist-info/METADATA
django_admin_keycloak-1.0.1.dist-info/WHEEL
django_admin_keycloak-1.0.1.dist-info/licenses/LICENSE
django_admin_keycloak-1.0.1.dist-info/RECORD
