Metadata-Version: 2.4
Name: django-admin-keycloak
Version: 1.0.1
Summary: Django Admin Keycloak
License-File: LICENSE
Keywords: keycloak,django
Author: Mikhail Badrazhan
Author-email: mikhail@devilweb.ru
Requires-Python: >=3.10,<4.0
Classifier: Framework :: Django :: 4
Classifier: Framework :: Django :: 5.0
Classifier: Programming Language :: Python :: 3
Classifier: Programming Language :: Python :: 3.10
Classifier: Programming Language :: Python :: 3.11
Classifier: Programming Language :: Python :: 3.12
Classifier: Programming Language :: Python :: 3.13
Classifier: Programming Language :: Python :: 3.14
Requires-Dist: django (>=4,<7)
Requires-Dist: python-keycloak (>=7.0.2,<8.0.0)
Project-URL: Repository, https://github.com/migelbd/django-admin-keycloak
